opentelemetry/environment_variables.py
opentelemetry/py.typed
opentelemetry/version.py
opentelemetry/attributes/__init__.py
opentelemetry/baggage/__init__.py
opentelemetry/baggage/propagation/__init__.py
opentelemetry/context/__init__.py
opentelemetry/context/context.py
opentelemetry/context/contextvars_context.py
opentelemetry/metrics/__init__.py
opentelemetry/metrics/_internal/__init__.py
opentelemetry/metrics/_internal/instrument.py
opentelemetry/metrics/_internal/observation.py
opentelemetry/propagate/__init__.py
opentelemetry/propagators/composite.py
opentelemetry/propagators/textmap.py
opentelemetry/trace/__init__.py
opentelemetry/trace/span.py
opentelemetry/trace/status.py
opentelemetry/trace/propagation/__init__.py
opentelemetry/trace/propagation/tracecontext.py
opentelemetry/util/_once.py
opentelemetry/util/_providers.py
opentelemetry/util/_time.py
opentelemetry/util/re.py
opentelemetry/util/types.py
opentelemetry_api-1.12.0.dist-info/LICENSE
opentelemetry_api-1.12.0.dist-info/METADATA
opentelemetry_api-1.12.0.dist-info/WHEEL
opentelemetry_api-1.12.0.dist-info/entry_points.txt
opentelemetry_api-1.12.0.dist-info/top_level.txt
opentelemetry_api-1.12.0.dist-info/RECORD
